itermark/__init__.py
itermark/_dict.py
itermark/_list.py
itermark/_ordict.py
itermark/_set.py
itermark/_str.py
itermark/_tuple.py
itermark/_z_itermark_engine.py
itermark-0.1.0.dist-info/LICENSE
itermark-0.1.0.dist-info/METADATA
itermark-0.1.0.dist-info/WHEEL
itermark-0.1.0.dist-info/top_level.txt
itermark-0.1.0.dist-info/RECORD
