Metadata-Version: 2.1
Name: itermark
Version: 0.1.0
Summary: Extension for iterable data types; adds boundwise bookmark iteration, enabling active item tracking/setting (type allowing)
Home-page: https://github.com/dpazavalos/Itermark
Author: Daniel Paz Avalos
Author-email: me@dpazavalos.dev
License: UNKNOWN
Platform: UNKNOWN
Classifier: Programming Language :: Python :: 3
Classifier: License :: OSI Approved :: MIT License
Classifier: Operating System :: OS Independent
